{
  "annotations": {
    "list": [
      {
        "builtIn": 1,
        "datasource": "-- Grafana --",
        "enable": true,
        "hide": true,
        "name": "Annotations & Alerts",
        "type": "dashboard"
      }
    ]
  },
  "editable": true,
  "fiscalYearStartMonth": 0,
  "graphTooltip": 0,
  "id": null,
  "links": [],
  "liveNow": false,
  "panels": [
    {
      "datasource": { "type": "prometheus", "uid": "Prometheus" },
      "fieldConfig": {
        "defaults": {
          "color": { "mode": "palette-classic" },
          "unit": "percentunit"
        }
      },
      "gridPos": { "h": 8, "w": 8, "x": 0, "y": 0 },
      "id": 1,
      "options": {
        "legend": { "displayMode": "list", "placement": "bottom" },
        "tooltip": { "mode": "single" }
      },
      "targets": [
        {
          "expr": "1 - (node_memory_MemAvailable_bytes / node_memory_MemTotal_bytes)",
          "refId": "A"
        }
      ],
      "title": "Memory Usage",
      "type": "timeseries"
    },
    {
      "datasource": { "type": "prometheus", "uid": "Prometheus" },
      "fieldConfig": {
        "defaults": {
          "color": { "mode": "palette-classic" },
          "unit": "percent"
        }
      },
      "gridPos": { "h": 8, "w": 8, "x": 8, "y": 0 },
      "id": 2,
      "options": {
        "legend": { "displayMode": "list", "placement": "bottom" }
      },
      "targets": [
        {
          "expr": "100 - (avg by(instance) (rate(node_cpu_seconds_total{mode='idle'}[5m])) * 100)",
          "refId": "A"
        }
      ],
      "title": "CPU Usage",
      "type": "timeseries"
    },
    {
      "datasource": { "type": "prometheus", "uid": "Prometheus" },
      "fieldConfig": {
        "defaults": {
          "color": { "mode": "palette-classic" },
          "unit": "bps"
        }
      },
      "gridPos": { "h": 8, "w": 8, "x": 16, "y": 0 },
      "id": 3,
      "options": {
        "legend": { "displayMode": "list", "placement": "bottom" }
      },
      "targets": [
        {
          "expr": "rate(node_network_receive_bytes_total[5m]) * 8",
          "legendFormat": "Inbound",
          "refId": "A"
        },
        {
          "expr": "rate(node_network_transmit_bytes_total[5m]) * 8",
          "legendFormat": "Outbound",
          "refId": "B"
        }
      ],
      "title": "Network Traffic",
      "type": "timeseries"
    },
    {
      "datasource": { "type": "prometheus", "uid": "Prometheus" },
      "fieldConfig": {
        "defaults": { "unit": "s" }
      },
      "gridPos": { "h": 8, "w": 24, "x": 0, "y": 8 },
      "id": 4,
      "targets": [
        {
          "expr": "avg(container_cpu_usage_seconds_total{container_label_com_docker_compose_service='app'})",
          "legendFormat": "App Latency (Estimate)",
          "refId": "A"
        }
      ],
      "title": "Service Response Time & Error Rate",
      "type": "timeseries"
    }
  ],
  "refresh": "5s",
  "schemaVersion": 36,
  "style": "dark",
  "tags": ["camwater", "infrastructure"],
  "templating": { "list": [] },
  "time": { "from": "now-1h", "to": "now" },
  "title": "CamwaterPRO Comprehensive Monitoring",
  "uid": "camwater_monitoring",
  "version": 2
}
